med_dataloader/__init__.py
med_dataloader/cli.py
med_dataloader/med_dataloader.py
med_dataloader-0.1.16.dist-info/AUTHORS.rst
med_dataloader-0.1.16.dist-info/LICENSE
med_dataloader-0.1.16.dist-info/METADATA
med_dataloader-0.1.16.dist-info/WHEEL
med_dataloader-0.1.16.dist-info/entry_points.txt
med_dataloader-0.1.16.dist-info/top_level.txt
med_dataloader-0.1.16.dist-info/RECORD
