Metadata-Version: 2.1
Name: med-dataloader
Version: 0.1.16
Summary: A general-purpose Dataloader for Tensorflow 2.x. It supports many medical image formats.
Home-page: https://github.com/mrossi93/med_dataloader
Author: Matteo Rossi
Author-email: rossimatteo1993@gmail.com
License: MIT license
Keywords: med_dataloader
Platform: UNKNOWN
Classifier: Development Status :: 2 - Pre-Alpha
Classifier: Intended Audience :: Developers
Classifier: License :: OSI Approved :: MIT License
Classifier: Natural Language :: English
Classifier: Programming Language :: Python :: 3
Classifier: Programming Language :: Python :: 3.7
Classifier: Programming Language :: Python :: 3.8
Requires-Python: >=3.5
License-File: LICENSE
License-File: AUTHORS.rst
Requires-Dist: tensorflow (>=2.4)
Requires-Dist: SimpleITK (>=2.0)
Requires-Dist: click
